LICENSE
README.md
setup.py
 BeardbAPI/BeardbAPI.py
 BeardbAPI/__init__.py
 BeardbAPI/shell.py
 BeardbAPI/app/__init__.py
 BeardbAPI/app/controllers/__init__.py
 BeardbAPI/app/controllers/pages.py
 BeardbAPI/config/__init__.py
 BeardbAPI/config/development/__init__.py
BeardbAPI.egg-info/PKG-INFO
BeardbAPI.egg-info/SOURCES.txt
BeardbAPI.egg-info/dependency_links.txt
BeardbAPI.egg-info/entry_points.txt
BeardbAPI.egg-info/requires.txt
BeardbAPI.egg-info/top_level.txt
tests/__init__.py
tests/helpers.py
tests/test_page.py