Metadata-Version: 2.1
Name: BeardbAPI
Version: 0.0.4
Summary: Microservice to deploy Beardb Secured Databases Remotely.
Home-page: https://github.com/teddyoweh/beardb-api
Author: Teddy Oweh
Author-email: teddy@teddyoweh.net
License: MIT
Classifier: License :: OSI Approved :: MIT License
Classifier: Programming Language :: Python :: 3
Classifier: Programming Language :: Python :: 3.7
License-File: LICENSE
